MANIFEST.in
README.md
setup.py
zoo_framework/__init__.py
zoo_framework/__main__.py
zoo_framework.egg-info/PKG-INFO
zoo_framework.egg-info/SOURCES.txt
zoo_framework.egg-info/dependency_links.txt
zoo_framework.egg-info/entry_points.txt
zoo_framework.egg-info/requires.txt
zoo_framework.egg-info/top_level.txt
zoo_framework/conf/__init__.py
zoo_framework/conf/log_config.py
zoo_framework/constant/__init__.py
zoo_framework/constant/waiter_constant.py
zoo_framework/constant/worker_constant.py
zoo_framework/core/__init__.py
zoo_framework/core/master.py
zoo_framework/core/meta_singleton.py
zoo_framework/core/params_factory.py
zoo_framework/core/params_path.py
zoo_framework/core/zoo_thread.py
zoo_framework/core/aop/__init__.py
zoo_framework/core/aop/cage.py
zoo_framework/core/aop/configure.py
zoo_framework/core/aop/event.py
zoo_framework/core/aop/params.py
zoo_framework/core/aop/validation.py
zoo_framework/core/aop/worker.py
zoo_framework/core/waiter/__init__.py
zoo_framework/core/waiter/base_waiter.py
zoo_framework/core/waiter/safe_waiter.py
zoo_framework/core/waiter/simple_waiter.py
zoo_framework/core/waiter/stable_waiter.py
zoo_framework/core/waiter/waiter_factory.py
zoo_framework/fifo/__init__.py
zoo_framework/fifo/base_fifo.py
zoo_framework/fifo/delay_fifo.py
zoo_framework/fifo/event_fifo.py
zoo_framework/fifo/single_fifo.py
zoo_framework/fifo/node/__init__.py
zoo_framework/fifo/node/delay_fifo_node.py
zoo_framework/fifo/node/event_fifo_node.py
zoo_framework/handler/__init__.py
zoo_framework/handler/base_handler.py
zoo_framework/handler/event_reactor.py
zoo_framework/handler/waiter_result_handler.py
zoo_framework/lock/__init__.py
zoo_framework/lock/base_lock.py
zoo_framework/params/__init__.py
zoo_framework/params/event_params.py
zoo_framework/params/log_params.py
zoo_framework/params/state_machine_params.py
zoo_framework/params/worker_params.py
zoo_framework/statemachine/__init__.py
zoo_framework/statemachine/base_state_machine.py
zoo_framework/statemachine/state_machine_manager.py
zoo_framework/templates/__init__.py
zoo_framework/templates/main.pyt
zoo_framework/templates/thread.pyt
zoo_framework/utils/__init__.py
zoo_framework/utils/cmd_utils.py
zoo_framework/utils/datetime_utils.py
