Metadata-Version: 2.1
Name: zoo-framework
Version: 0.4.1
Summary: A simple and quick multi-threaded framework
Home-page: UNKNOWN
Author: XiangMeng
Author-email: mengxiang931015@live.com
License: Apache License
Platform: all
Classifier: Intended Audience :: Developers
Classifier: Operating System :: OS Independent
Classifier: Natural Language :: Chinese (Simplified)
Classifier: Programming Language :: Python
Classifier: Programming Language :: Python :: 3
Classifier: Programming Language :: Python :: 3.5
Classifier: Programming Language :: Python :: 3.6
Classifier: Programming Language :: Python :: 3.7
Classifier: Programming Language :: Python :: 3.8
Classifier: Topic :: Software Development :: Libraries
